dg_chatgpt/__init__.py
dg_chatgpt/chatgpt.py
dg_chatgpt/config.py
dg_chatgpt/models.py
dg_chatgpt-0.1.5.dist-info/LICENSE
dg_chatgpt-0.1.5.dist-info/METADATA
dg_chatgpt-0.1.5.dist-info/WHEEL
dg_chatgpt-0.1.5.dist-info/top_level.txt
dg_chatgpt-0.1.5.dist-info/RECORD
