Metadata-Version: 2.1
Name: dg-chatgpt
Version: 0.1.5
Summary: Wrapper for OpenAI API, intended to be used for a discord bot powered by chatGPT.
Author-email: Ondřej Moravec <moravec@devground.cz>
Project-URL: Homepage, https://github.com/hkcmoris/dg_chatgpt
Project-URL: Bugtracker, https://github.com/hkcmoris/dg_chatgpt/issues
Classifier: Development Status :: 3 - Alpha
Classifier: Intended Audience :: Developers
Classifier: Programming Language :: Python :: 3
Classifier: License :: OSI Approved :: MIT License
Classifier: Operating System :: OS Independent
Classifier: Topic :: Software Development :: Libraries :: Python Modules
Requires-Python: >=3.7
License-File: LICENSE
Requires-Dist: openai
Requires-Dist: python-dotenv
Requires-Dist: requests
